odoo/addons/account_bank_statement_import_online_adyen/README.rst
odoo/addons/account_bank_statement_import_online_adyen/__init__.py
odoo/addons/account_bank_statement_import_online_adyen/__manifest__.py
odoo/addons/account_bank_statement_import_online_adyen/i18n/account_bank_statement_import_online_adyen.pot
odoo/addons/account_bank_statement_import_online_adyen/models/__init__.py
odoo/addons/account_bank_statement_import_online_adyen/models/account_journal.py
odoo/addons/account_bank_statement_import_online_adyen/models/online_bank_statement_provider.py
odoo/addons/account_bank_statement_import_online_adyen/readme/CONFIGURE.rst
odoo/addons/account_bank_statement_import_online_adyen/readme/CONTRIBUTORS.rst
odoo/addons/account_bank_statement_import_online_adyen/readme/DESCRIPTION.rst
odoo/addons/account_bank_statement_import_online_adyen/readme/USAGE.rst
odoo/addons/account_bank_statement_import_online_adyen/static/description/icon.png
odoo/addons/account_bank_statement_import_online_adyen/static/description/index.html
odoo/addons/account_bank_statement_import_online_adyen/tests/__init__.py
odoo/addons/account_bank_statement_import_online_adyen/tests/online_bank_statement_provider_dummy.py
odoo/addons/account_bank_statement_import_online_adyen/tests/test_import_online.py
odoo/addons/account_bank_statement_import_online_adyen/views/online_bank_statement_provider.xml
odoo13_addon_account_bank_statement_import_online_adyen-13.0.1.0.1.dev10.dist-info/METADATA
odoo13_addon_account_bank_statement_import_online_adyen-13.0.1.0.1.dev10.dist-info/WHEEL
odoo13_addon_account_bank_statement_import_online_adyen-13.0.1.0.1.dev10.dist-info/top_level.txt
odoo13_addon_account_bank_statement_import_online_adyen-13.0.1.0.1.dev10.dist-info/RECORD
