Metadata-Version: 2.1
Name: odoo13-addon-account-bank-statement-import-online-adyen
Version: 13.0.1.0.1.dev10
Summary: Online Bank Statements: Adyen payment report
Home-page: https://github.com/OCA/bank-statement-import
Author: Ronald Portier (Therp BV), Odoo Community Association (OCA)
Author-email: support@odoo-community.org
License: AGPL-3
Platform: UNKNOWN
Classifier: Programming Language :: Python
Classifier: Framework :: Odoo
Classifier: Framework :: Odoo :: 13.0
Classifier: License :: OSI Approved :: GNU Affero General Public License v3
Requires-Python: >=3.5
Requires-Dist: odoo13-addon-account-bank-statement-import-adyen
Requires-Dist: odoo13-addon-account-bank-statement-import-online
Requires-Dist: odoo <13.1dev,>=13.0a
